[
    {"link": "https://www.8notes.com/piano_chord_chart/Eb.asp", "name": "1. Eb major"},
    {"link": "https://www.8notes.com/piano_chord_chart/Ebm.asp", "name": "2. Eb minor"},
    {"link": "https://www.8notes.com/piano_chord_chart/Eb7.asp", "name": "3. Eb 7"},
    {"link": "https://www.8notes.com/piano_chord_chart/Ebm7.asp", "name": "4. Eb m7"},
    {"link": "https://www.8notes.com/piano_chord_chart/Ebmaj7.asp", "name": "5. Eb maj7"},
    {"link": "https://www.8notes.com/piano_chord_chart/Ebmx7.asp", "name": "6. Eb m#7 (mM7)"},
    {"link": "https://www.8notes.com/piano_chord_chart/Eb7b5.asp", "name": "7. Eb 7b5"},
    {"link": "https://www.8notes.com/piano_chord_chart/Eb7x5.asp", "name": "8. Eb 7#5"},
    {"link": "https://www.8notes.com/piano_chord_chart/Ebm7b5.asp", "name": "9. Eb m7b5"},
    {"link": "https://www.8notes.com/piano_chord_chart/Eb7b9.asp", "name": "10. Eb 7b9"},
    {"link": "https://www.8notes.com/piano_chord_chart/Ebmajb5.asp", "name": "11. Eb b5"},
    {"link": "https://www.8notes.com/piano_chord_chart/Eb5.asp", "name": "12. Eb 5 Power Chord"},
    {"link": "https://www.8notes.com/piano_chord_chart/Eb6.asp", "name": "13. Eb 6"},
    {"link": "https://www.8notes.com/piano_chord_chart/Ebm6.asp", "name": "14. Eb m6"},
    {"link": "https://www.8notes.com/piano_chord_chart/Eb69.asp", "name": "15. Eb 69"},
    {"link": "https://www.8notes.com/piano_chord_chart/Eb9.asp", "name": "16. Eb 9"},
    {"link": "https://www.8notes.com/piano_chord_chart/Eb9b5.asp", "name": "17. Eb 9b5"},
    {"link": "https://www.8notes.com/piano_chord_chart/Eb9x5.asp", "name": "18. Eb 9#5"},
    {"link": "https://www.8notes.com/piano_chord_chart/Ebm9.asp", "name": "19. Eb m9"},
    {"link": "https://www.8notes.com/piano_chord_chart/Ebmaj9.asp", "name": "20. Eb maj9"},
    {"link": "https://www.8notes.com/piano_chord_chart/Ebadd9.asp", "name": "21. Eb add9"},
    {"link": "https://www.8notes.com/piano_chord_chart/Eb7x9.asp", "name": "22. Eb 7#9"},
    {"link": "https://www.8notes.com/piano_chord_chart/Eb11.asp", "name": "23. Eb 11"},
    {"link": "https://www.8notes.com/piano_chord_chart/Ebm11.asp", "name": "24. Eb m11"},
    {"link": "https://www.8notes.com/piano_chord_chart/Eb13.asp", "name": "25. Eb 13"},
    {"link": "https://www.8notes.com/piano_chord_chart/Ebmaj13.asp", "name": "26. Eb maj13"},
    {"link": "https://www.8notes.com/piano_chord_chart/Ebsus2.asp", "name": "27. Eb sus2"},
    {"link": "https://www.8notes.com/piano_chord_chart/Ebsus4.asp", "name": "28. Eb sus4"},
    {"link": "https://www.8notes.com/piano_chord_chart/Eb7sus4.asp", "name": "29. Eb7 sus4"},
    {"link": "https://www.8notes.com/piano_chord_chart/Eb9sus4.asp", "name": "30. Eb9 sus4"},
    {"link": "https://www.8notes.com/piano_chord_chart/Ebdim.asp", "name": "31. Eb dim"},
    {"link": "https://www.8notes.com/piano_chord_chart/Ebm7b5.asp", "name": "32. Eb half dim"},
    {"link": "https://www.8notes.com/piano_chord_chart/Ebdim7.asp", "name": "33. Eb dim7"},
    {"link": "https://www.8notes.com/piano_chord_chart/Ebaug.asp", "name": "34. Eb aug"},
    {"link": "https://www.8notes.com/piano_chord_chart/eb_g-bass.asp", "name": "35. Eb/G"},
    {"link": "https://www.8notes.com/piano_chord_chart/eb_bb-bass.asp", "name": "36. Eb/Bb"},
    {"link": "https://www.8notes.com/piano_chord_chart/eb_d-bass.asp", "name": "37. Eb/D"},
    {"link": "https://www.8notes.com/piano_chord_chart/eb_db-bass.asp", "name": "38. Eb/Db"},
    {"link": "https://www.8notes.com/piano_chord_chart/eb_f-bass.asp", "name": "39. Eb/F" }
]
